notebook_shim/__init__.py
notebook_shim/_version.py
notebook_shim/conftest.py
notebook_shim/nbserver.py
notebook_shim/shim.py
notebook_shim/traits.py
notebook_shim/tests/__init__.py
notebook_shim/tests/mockextension.py
notebook_shim/tests/test_extension.py
notebook_shim/tests/confs/jupyter_my_ext_config.py
notebook_shim/tests/confs/jupyter_notebook_config.py
notebook_shim/tests/confs/jupyter_server_config.py
notebook_shim-0.1.0.data/data/etc/jupyter/jupyter_server_config.d/notebook_shim.json
notebook_shim-0.1.0.dist-info/LICENSE
notebook_shim-0.1.0.dist-info/METADATA
notebook_shim-0.1.0.dist-info/WHEEL
notebook_shim-0.1.0.dist-info/top_level.txt
notebook_shim-0.1.0.dist-info/RECORD
