Metadata-Version: 2.1
Name: notebook_shim
Version: 0.1.0
Summary: A shim layer for notebook traits and config
Home-page: https://github.com/jupyterlab/notebook_shim
Author: Jupyter Development Team
Author-email: jupyter@googlegroups.com
License: UNKNOWN
Keywords: ipython,jupyter
Platform: Linux
Platform: Mac OS X
Platform: Windows
Classifier: Intended Audience :: Developers
Classifier: Intended Audience :: System Administrators
Classifier: Intended Audience :: Science/Research
Classifier: License :: OSI Approved :: BSD License
Classifier: Programming Language :: Python
Classifier: Programming Language :: Python :: 3.7
Classifier: Programming Language :: Python :: 3.8
Classifier: Programming Language :: Python :: 3.9
Classifier: Programming Language :: Python :: 3.10
Requires-Python: >=3.7
Provides-Extra: test
License-File: LICENSE
